helpme_kratik/__init__.py
helpme_kratik/helpme_kratik.py
helpme_kratik-0.5.0.dist-info/AUTHORS.rst
helpme_kratik-0.5.0.dist-info/LICENSE
helpme_kratik-0.5.0.dist-info/METADATA
helpme_kratik-0.5.0.dist-info/WHEEL
helpme_kratik-0.5.0.dist-info/top_level.txt
helpme_kratik-0.5.0.dist-info/RECORD
