Metadata-Version: 2.1
Name: helpme_kratik
Version: 0.5.0
Summary: Python Boilerplate contains all the boilerplate you need to create a Python package.
Home-page: https://github.com/KratikJain10/helpme-kratik.git
Author: Kratik Jain
Author-email: Kratik Jain <kratikjain1520@gmail.com>
Maintainer-email: Kratik Jain <kratikjain1520@gmail.com>
License: MIT license
Project-URL: bugs, https://github.com/KratikJain10/helpme_kratik/issues
Project-URL: changelog, https://github.com/KratikJain10/helpme_kratik/blob/master/changelog.md
Project-URL: homepage, https://github.com/KratikJain10/helpme_kratik
License-File: LICENSE
License-File: AUTHORS.rst
Provides-Extra: dev
Requires-Dist: coverage; extra == "dev"
Requires-Dist: mypy; extra == "dev"
Requires-Dist: pytest; extra == "dev"
Requires-Dist: ruff; extra == "dev"
